pydvenv/__init__.py
pydvenv/pydvenv.py
pydvenv-1.0.0.dist-info/METADATA
pydvenv-1.0.0.dist-info/WHEEL
pydvenv-1.0.0.dist-info/entry_points.txt
pydvenv-1.0.0.dist-info/top_level.txt
pydvenv-1.0.0.dist-info/RECORD
