Metadata-Version: 2.4
Name: pydvenv
Version: 1.0.0
Summary: Creating a directory with a Python virtual environment
Home-page: https://github.com/MagIlyasDOMA/pydvenv
Author: Маг Ильяс DOMA (MagIlyasDOMA)
Author-email: magilyas.doma.09@list.ru
Classifier: License :: OSI Approved :: MIT License
Classifier: Operating System :: OS Independent
Classifier: Development Status :: 5 - Production/Stable
Classifier: Programming Language :: Python
Classifier: Programming Language :: Python :: 3
Classifier: Programming Language :: Python :: 3.10
Classifier: Programming Language :: Python :: 3.11
Classifier: Programming Language :: Python :: 3.12
Classifier: Programming Language :: Python :: 3.13
Classifier: Programming Language :: Python :: 3.14
Classifier: Topic :: Software Development :: Libraries
Classifier: Topic :: Software Development :: Libraries :: Python Modules
Requires-Python: >=3.10
Provides-Extra: dev
Requires-Dist: pip-setuptools>=1.1.4; extra == "dev"
Dynamic: author
Dynamic: author-email
Dynamic: classifier
Dynamic: description
Dynamic: description-content-type
Dynamic: home-page
Dynamic: provides-extra
Dynamic: requires-python
Dynamic: summary
